hatenagraph.py
setup.py
hatenagraph.egg-info/PKG-INFO
hatenagraph.egg-info/SOURCES.txt
hatenagraph.egg-info/dependency_links.txt
hatenagraph.egg-info/requires.txt
hatenagraph.egg-info/top_level.txt