Metadata-Version: 1.0
Name: hatenagraph
Version: 0.1
Summary: A python wrapper around the Hatena Graph API
Home-page: UNKNOWN
Author: Yoshiori SHOJI
Author-email: yoshiori@google.com
License: UNKNOWN
Platform: UNKNOWN
